{
  "coc.preferences.extensionUpdateCheck": "weekly",
  "coc.preferences.hoverTarget": "float",
  "list.previousKeymap": "<C-p>",
  "list.nextKeymap": "<C-n>",
  "diagnostic.displayByAle": false,
  "clangd.enabled": false,
  "coc.preferences.formatOnSaveFiletypes": [
    "json",
    "rust"
  ],
  "pairs.disableLanguages": [],
  "languageserver": {
    "ccls": {
      "command": "ccls",
      "filetypes": [
        "c",
        "cpp",
        "objc",
        "objcpp"
      ],
      "rootPatterns": [
        ".ccls",
        "compile_commands.json",
        ".vim/",
        ".git/",
        ".hg/"
      ],
      "initializationOptions": {
        "cache": {
          "directory": "/tmp/ccls"
        }
      }
    }
  }
}
